ch/__init__.py
ch/qos/__init__.py
ch/qos/logback/__init__.py
ch/qos/logback/classic/__init__.py
com/__init__.py
com/codahale/__init__.py
com/codahale/metrics/__init__.py
com/google/__init__.py
com/google/common/__init__.py
com/google/common/collect/__init__.py
com/google/common/eventbus/__init__.py
com/google/common/util/__init__.py
com/google/common/util/concurrent/__init__.py
com/inductiveautomation/__init__.py
com/inductiveautomation/factorypmi/__init__.py
com/inductiveautomation/factorypmi/application/__init__.py
com/inductiveautomation/factorypmi/application/binding/__init__.py
com/inductiveautomation/factorypmi/application/components/__init__.py
com/inductiveautomation/factorypmi/application/model/__init__.py
com/inductiveautomation/factorypmi/application/script/__init__.py
com/inductiveautomation/factorypmi/application/script/builtin/__init__.py
com/inductiveautomation/factorypmi/application/sqltags/__init__.py
com/inductiveautomation/factorypmi/application/sqltags/project/__init__.py
com/inductiveautomation/ignition/__init__.py
com/inductiveautomation/ignition/alarming/__init__.py
com/inductiveautomation/ignition/alarming/common/__init__.py
com/inductiveautomation/ignition/alarming/common/rosters/__init__.py
com/inductiveautomation/ignition/client/__init__.py
com/inductiveautomation/ignition/client/launch/__init__.py
com/inductiveautomation/ignition/client/model/__init__.py
com/inductiveautomation/ignition/client/util/__init__.py
com/inductiveautomation/ignition/client/util/gui/__init__.py
com/inductiveautomation/ignition/client/util/gui/progress/__init__.py
com/inductiveautomation/ignition/client/util/gui/scheduling/__init__.py
com/inductiveautomation/ignition/common/__init__.py
com/inductiveautomation/ignition/common/alarming/__init__.py
com/inductiveautomation/ignition/common/alarming/evaluation/__init__.py
com/inductiveautomation/ignition/common/alarming/query/__init__.py
com/inductiveautomation/ignition/common/binding/__init__.py
ignition_api-8.3.3.dist-info/LICENSE
ignition_api-8.3.3.dist-info/METADATA
ignition_api-8.3.3.dist-info/WHEEL
ignition_api-8.3.3.dist-info/top_level.txt
ignition_api-8.3.3.dist-info/RECORD
