Metadata-Version: 2.1
Name: ignition-api
Version: 8.3.3
Summary: Ignition Scripting API
Home-page: https://github.com/ignition-devs/ignition-api
Author: César Román
Author-email: cesar@coatl.dev
License: MIT
Project-URL: Source, https://github.com/ignition-devs/ignition-api/tree/8.3
Project-URL: Documentation, https://docs.inductiveautomation.com/docs/8.3/appendix/scripting-functions
Project-URL: Funding, https://github.com/sponsors/cesarcoatl
Project-URL: Tracker, https://github.com/ignition-devs/ignition-api/issues
Keywords: hmi,ignition,inductive automation,scada
Platform: UNKNOWN
Classifier: Development Status :: 5 - Production/Stable
Classifier: Intended Audience :: Developers
Classifier: Intended Audience :: Information Technology
Classifier: Intended Audience :: Manufacturing
Classifier: Operating System :: MacOS :: MacOS X
Classifier: Operating System :: Microsoft :: Windows
Classifier: Operating System :: POSIX :: Linux
Classifier: Programming Language :: Python
Classifier: Programming Language :: Python :: 2
Classifier: Programming Language :: Python :: 2 :: Only
Classifier: Programming Language :: Python :: 2.7
Classifier: Topic :: Software Development :: Libraries :: Python Modules
Classifier: Topic :: Software Development :: Testing :: Mocking
Requires-Python: ==2.7.18
Requires-Dist: enum34
Requires-Dist: java-api
